{
  "description": "Double Shift To Command Control Slash",
  "manipulators": [
    {
      "conditions": [
        {
          "name": "left_shift pressed",
          "type": "variable_if",
          "value": 1
        }
      ],
      "from": {
        "key_code": "left_shift",
        "modifiers": { "optional": ["any"] }
      },
      "to": [
        {
          "key_code": "slash",
          "modifiers": ["left_command", "left_control"]
        }
      ],
      "type": "basic"
    },
    {
      "from": {
        "key_code": "left_shift",
        "modifiers": { "optional": ["any"] }
      },
      "parameters": {
        "basic.to_delayed_action_delay_milliseconds": 800,
        "basic.to_if_alone_timeout_milliseconds": 300
      },
      "to": [
        {
          "set_variable": {
            "name": "left_shift pressed",
            "value": 1
          }
        },
        { "key_code": "left_shift" }
      ],
      "to_delayed_action": {
        "to_if_canceled": [
          {
            "set_variable": {
              "name": "left_shift pressed",
              "value": 0
            }
          }
        ],
        "to_if_invoked": [
          {
            "set_variable": {
              "name": "left_shift pressed",
              "value": 0
            }
          }
        ]
      },
      "type": "basic"
    }
  ]
}
